LICENSE
MANIFEST.in
README.rst
requirements.txt
setup.py
narwal/__init__.py
narwal/const.py
narwal/exceptions.py
narwal/reddit.py
narwal/things.py
narwal/util.py
narwal.egg-info/PKG-INFO
narwal.egg-info/SOURCES.txt
narwal.egg-info/dependency_links.txt
narwal.egg-info/requires.txt
narwal.egg-info/top_level.txt