Metadata-Version: 1.0
Name: narwal
Version: 0.2.4a
Summary: A thin wrapper for the Reddit API.
Home-page: https://github.com/larryng/narwal
Author: Larry Ng
Author-email: ng.larry@gmail.com
License: UNKNOWN
Keywords: reddit,api,wrapper
Platform: UNKNOWN
Classifier: Programming Language :: Python :: 2.7
Classifier: Development Status :: 3 - Alpha
Classifier: Environment :: Web Environment
Classifier: Intended Audience :: Developers
Classifier: License :: OSI Approved :: ISC License (ISCL)
Classifier: Natural Language :: English
Classifier: Operating System :: OS Independent
Classifier: Topic :: Utilities
